pySQLWrapper/__init__.py
pySQLWrapper/postgresql.py
pySQLWrapper-0.12.dist-info/LICENSE
pySQLWrapper-0.12.dist-info/METADATA
pySQLWrapper-0.12.dist-info/WHEEL
pySQLWrapper-0.12.dist-info/top_level.txt
pySQLWrapper-0.12.dist-info/RECORD
