Metadata-Version: 2.1
Name: pySQLWrapper
Version: 0.12
Summary: A SQL wrapper library to make easy to build SQL interfaces
Home-page: https://github.com/LukasGrudtner/sql-wrapper
Download-URL: https://github.com/LukasGrudtner/sql-wrapper/archive/refs/tags/v0.1.tar.gz
Author: Lukas Grüdtner
Author-email: lukasgrudtner@hotmail.com
License: MIT
Keywords: SQL,SQL Wrapper,PostgreSQL
Classifier: Development Status :: 3 - Alpha
Classifier: Intended Audience :: Developers
Classifier: Topic :: Software Development :: Build Tools
Classifier: License :: OSI Approved :: MIT License
Classifier: Programming Language :: Python :: 3
Classifier: Programming Language :: Python :: 3.4
Classifier: Programming Language :: Python :: 3.5
Classifier: Programming Language :: Python :: 3.6
License-File: LICENSE
